imaginarydate
